typer_to_textual/__init__.py
typer_to_textual/__main__.py
typer_to_textual/command_options.py
typer_to_textual/homepage.py
typer_to_textual/main.py
typer_to_textual/show.py
typer_to_textual/style.css
typer_to_textual-2.5.0.dist-info/METADATA
typer_to_textual-2.5.0.dist-info/WHEEL
typer_to_textual-2.5.0.dist-info/RECORD
