Metadata-Version: 2.1
Name: typer-to-textual
Version: 2.5.0
Summary: 
Author: palla98
Author-email: pallaria98@gmail.com
Requires-Python: >=3.9,<4.0
Classifier: Programming Language :: Python :: 3
Classifier: Programming Language :: Python :: 3.9
Classifier: Programming Language :: Python :: 3.10
Classifier: Programming Language :: Python :: 3.11
Requires-Dist: rich (>=13.3.2,<14.0.0)
Requires-Dist: textual (>=0.10.1,<0.11.0)
Requires-Dist: typer (>=0.7.0,<0.8.0)
Requires-Dist: xdotool (>=0.4.0,<0.5.0) ; python_version >= "3.10" and python_version < "4.0"
